ja_ginza/__init__.py
ja_ginza/meta.json
ja_ginza/ja_ginza-5.2.0/README.md
ja_ginza/ja_ginza-5.2.0/config.cfg
ja_ginza/ja_ginza-5.2.0/meta.json
ja_ginza/ja_ginza-5.2.0/attribute_ruler/patterns
ja_ginza/ja_ginza-5.2.0/compound_splitter/cfg
ja_ginza/ja_ginza-5.2.0/morphologizer/cfg
ja_ginza/ja_ginza-5.2.0/morphologizer/model
ja_ginza/ja_ginza-5.2.0/ner/cfg
ja_ginza/ja_ginza-5.2.0/ner/model
ja_ginza/ja_ginza-5.2.0/ner/moves
ja_ginza/ja_ginza-5.2.0/parser/cfg
ja_ginza/ja_ginza-5.2.0/parser/model
ja_ginza/ja_ginza-5.2.0/parser/moves
ja_ginza/ja_ginza-5.2.0/tok2vec/cfg
ja_ginza/ja_ginza-5.2.0/tok2vec/model
ja_ginza/ja_ginza-5.2.0/tokenizer/cfg
ja_ginza/ja_ginza-5.2.0/vocab/key2row
ja_ginza/ja_ginza-5.2.0/vocab/lookups.bin
ja_ginza/ja_ginza-5.2.0/vocab/strings.json
ja_ginza/ja_ginza-5.2.0/vocab/vectors
ja_ginza/ja_ginza-5.2.0/vocab/vectors.cfg
ja_ginza-5.2.0.dist-info/METADATA
ja_ginza-5.2.0.dist-info/WHEEL
ja_ginza-5.2.0.dist-info/entry_points.txt
ja_ginza-5.2.0.dist-info/top_level.txt
ja_ginza-5.2.0.dist-info/RECORD
