Metadata-Version: 2.1
Name: ja-ginza
Version: 5.2.0
Summary: Japanese multi-task CNN trained on UD-Japanese BCCWJ r2.8 + GSK2014-A(2019). Assigns word2vec token vectors. Components: tok2vec, parser, ner, morphologizer, atteribute_ruler, compound_splitter, bunsetu_recognizer.
Home-page: https://github.com/megagonlabs/ginza
Author: Megagon Labs Tokyo.
Author-email: ginza@megagon.ai
License: MIT License
